AUTHORS
COPYING
ChangeLog
README.md
requirements.txt
setup.cfg
setup.py
cometblue/__init__.py
cometblue/cli.py
cometblue/device.py
cometblue/discovery.py
cometblue.egg-info/PKG-INFO
cometblue.egg-info/SOURCES.txt
cometblue.egg-info/dependency_links.txt
cometblue.egg-info/entry_points.txt
cometblue.egg-info/not-zip-safe
cometblue.egg-info/pbr.json
cometblue.egg-info/requires.txt
cometblue.egg-info/top_level.txt