Metadata-Version: 1.1
Name: cometblue
Version: 0.1.2
Summary: Command line tool and python library for "Comet Blue" radiator thermostat
Home-page: https://github.com/im-0/cometblue
Author: Ivan Mironov
Author-email: mironov.ivan@gmail.com
License: UNKNOWN
Keywords: cometblue bluetooth ble gatt
Platform: UNKNOWN
Classifier: Development Status :: 4 - Beta
Classifier: Environment :: Console
Classifier: Intended Audience :: Developers
Classifier: Intended Audience :: End Users/Desktop
Classifier: License :: OSI Approved :: GNU General Public License v3 or later (GPLv3+)
Classifier: Operating System :: POSIX :: Linux
Classifier: Programming Language :: Python :: 2
Classifier: Programming Language :: Python :: 2.7
